AUTHORS
LICENSE
MANIFEST.in
README.rst
setup.py
antidogpiling/__init__.py
antidogpiling.egg-info/PKG-INFO
antidogpiling.egg-info/SOURCES.txt
antidogpiling.egg-info/dependency_links.txt
antidogpiling.egg-info/top_level.txt
antidogpiling.egg-info/zip-safe
antidogpiling/django/__init__.py
antidogpiling/django/common.py
antidogpiling/django/db.py
antidogpiling/django/dummy.py
antidogpiling/django/filebased.py
antidogpiling/django/locmem.py
antidogpiling/django/memcached.py