Metadata-Version: 1.0
Name: antidogpiling
Version: 1.1.3
Summary: Generic and specific implementations of anti-dogpiled caching
Home-page: http://github.com/torgeilo/antidogpiling
Author: Torgeir Lorange Østby
Author-email: torgeilo@gmail.com
License: BSD
Keywords: cache caching anti-dogpiling dogpiling
Platform: UNKNOWN
Classifier: Framework :: Django
Classifier: Intended Audience :: Developers
Classifier: License :: OSI Approved :: BSD License
Classifier: Operating System :: OS Independent
Classifier: Programming Language :: Python
Classifier: Topic :: Software Development
